poetry_demo_alphaae/__init__.py
poetry_demo_alphaae/main.py
poetry_demo_alphaae-0.1.0.dist-info/WHEEL
poetry_demo_alphaae-0.1.0.dist-info/METADATA
poetry_demo_alphaae-0.1.0.dist-info/RECORD
