Metadata-Version: 2.1
Name: poetry-demo-alphaae
Version: 0.1.0
Summary: 
Author: alphaAE
Author-email: a1226123914@gmail.com
Requires-Python: >=3.9,<4.0
Classifier: Programming Language :: Python :: 3
Classifier: Programming Language :: Python :: 3.10
Classifier: Programming Language :: Python :: 3.9
Requires-Dist: numpy (>=1.22.1,<2.0.0)
